{
  "0x05fF2B0DB69458A0750badebc4f9e13aDd608C7F": {
    "name": "PancakeSwap",
    "type": "contract",
    "dateAdded": "2021-01-19",
    "logo": "https://app.soteria.finance/images/pancake.svg",
    "github": "https://github.com/pancakeswap",
    "messari": ""
  },
  "0xE02dF9e3e622DeBdD69fb838bB799E3F168902c5": {
    "name": "BakerySwap",
    "type": "contract",
    "dateAdded": "2021-01-25",
    "logo": "https://app.soteria.finance/images/bakery.png",
    "github": "https://github.com/BakeryProject",
    "messari": ""
  },
  "0x63870A18B6e42b01Ef1Ad8A2302ef50B7132054F": {
    "name": "Blink",
    "type": "contract",
    "dateAdded": "2021-01-27",
    "logo": "https://app.soteria.finance/images/blink.png",
    "github": "https://blink.wink.org",
    "messari": ""
  },
  "0x4cd1761aF5c771fb4046ED0F6eD39239f466f63B": {
    "name": "SPHINX",
    "type": "contract",
    "dateAdded": "2021-01-29",
    "logo": "https://app.soteria.finance/images/sphinx.png",
    "github": "https://sphinx.finance",
    "messari": ""
  },
  "0x5Ac52EE5b2a633895292Ff6d8A89bB9190451587": {
    "name": "BSCEX",
    "type": "contract",
    "dateAdded": "2021-02-01",
    "logo": "https://app.soteria.finance/images/bscex.png",
    "github": "https://github.com/Bscex",
    "messari": ""
  },
  "0x4A9A2b2b04549C3927dd2c9668A5eF3fCA473623": {
    "name": "dForce(BSC)",
    "type": "contract",
    "dateAdded": "2021-02-02",
    "logo": "https://app.soteria.finance/images/dforce.png",
    "github": "https://github.com/dforce-network",
    "messari": ""
  },
  "0xc78248D676DeBB4597e88071D3d889eCA70E5469": {
    "name": "ForTube(BSC)",
    "type": "contract",
    "dateAdded": "2021-02-03",
    "logo": "https://app.soteria.finance/images/fortube.png",
    "github": "https://github.com/thefortube",
    "messari": ""
  },
  "0xb8C540d00dd0Bf76ea12E4B4B95eFC90804f924E": {
    "name": "QIAN(BSC)",
    "type": "contract",
    "dateAdded": "2021-02-04",
    "logo": "https://app.soteria.finance/images/qian.png",
    "github": "https://github.com/QIAN-Protocol",
    "messari": ""
  }
}
